sewergraph/__init__.py
sewergraph/area_calcs.py
sewergraph/core.py
sewergraph/cost_estimates.py
sewergraph/helpers.py
sewergraph/hhcalculations.py
sewergraph/kpi.py
sewergraph/plot.py
sewergraph/resolve_data.py
sewergraph/save_load.py
sewergraph/tests/__init__.py
sewergraph/tests/accumulation_test.py
sewergraph/tests/net_resolution_test.py
sewergraph/tests/test_hhcalculations.py
sewergraph-0.1.4.dist-info/METADATA
sewergraph-0.1.4.dist-info/WHEEL
sewergraph-0.1.4.dist-info/top_level.txt
sewergraph-0.1.4.dist-info/RECORD
