Metadata-Version: 2.1
Name: sewergraph
Version: 0.1.4
Summary: Tools for graph calculations on sewer networks
Home-page: https://github.com/aerispaha/sewergraph
Author: Adam Erispaha
Author-email: aerispaha@gmail.com
License: MIT License
Platform: OS Independent
Classifier: Development Status :: 3 - Alpha
Classifier: License :: OSI Approved :: MIT License
Classifier: Operating System :: OS Independent
Classifier: Programming Language :: Python :: 2.7
Classifier: Programming Language :: Python :: 3.6
Requires-Dist: pandas
Requires-Dist: networkx (>=2)
Requires-Dist: numpy
